sgio/__init__.py
sgio/__main__.py
sgio/_exceptions.py
sgio/_global.py
sgio/_version.py
sgio/app.py
sgio/execu.py
sgio/_vendors/__init__.py
sgio/_vendors/inprw/NoneSort.py
sgio/_vendors/inprw/__init__.py
sgio/_vendors/inprw/centroid.py
sgio/_vendors/inprw/config.py
sgio/_vendors/inprw/config_re.py
sgio/_vendors/inprw/csid.py
sgio/_vendors/inprw/elType.py
sgio/_vendors/inprw/eval2.py
sgio/_vendors/inprw/inpDecimal.py
sgio/_vendors/inprw/inpInt.py
sgio/_vendors/inprw/inpKeyword.py
sgio/_vendors/inprw/inpKeywordHelper.py
sgio/_vendors/inprw/inpKeywordSequence.py
sgio/_vendors/inprw/inpRWErrors.py
sgio/_vendors/inprw/inpString.py
sgio/_vendors/inprw/mesh.py
sgio/_vendors/inprw/misc_functions.py
sgio/_vendors/inprw/paramTypes.py
sgio/_vendors/inprw/printer.py
sgio/_vendors/inprw/repr2.py
sgio/_vendors/inprw/inpRW/Read_Disclaimer_First.txt
sgio/_vendors/inprw/inpRW/__init__.py
sgio/_vendors/inprw/inpRW/_importedModules.py
sgio/_vendors/inprw/inpRW/_inpCustom.py
sgio/_vendors/inprw/inpRW/_inpFind.py
sgio/_vendors/inprw/inpRW/_inpFindRefs.py
sgio/_vendors/inprw/inpRW/_inpMod.py
sgio/_vendors/inprw/inpRW/_inpR.py
sgio/_vendors/inprw/inpRW/_inpW.py
sgio/_vendors/inprw/inpRW/elInfoDict.txt
sgio/_vendors/inprw/inpRW/keyword_names.txt
sgio/_vendors/inprw/inpRW/keyword_sub.txt
sgio/_vendors/inprw/inpRW/legal_notices.pdf
sgio/_vendors/inprw/inpRW-2023.10.6.dist-info/METADATA
sgio/_vendors/inprw/inpRW-2023.10.6.dist-info/RECORD
sgio/_vendors/inprw/inpRW-2023.10.6.dist-info/WHEEL
sgio/_vendors/inprw/inpRW-2023.10.6.dist-info/license.txt
sgio/_vendors/inprw/inpRW-2023.10.6.dist-info/top_level.txt
sgio/core/__init__.py
sgio/core/builder.py
sgio/core/merge.py
sgio/core/mesh.py
sgio/core/sg.py
sgio/iofunc/__init__.py
sgio/iofunc/_meshio.py
sgio/iofunc/main.py
sgio/iofunc/abaqus/__init__.py
sgio/iofunc/abaqus/_abaqus.py
sgio/iofunc/abaqus/_abaqus_old.py
sgio/iofunc/gmsh/__init__.py
sgio/iofunc/gmsh/_common.py
sgio/iofunc/gmsh/_gmsh.py
sgio/iofunc/gmsh/_gmsh22.py
sgio/iofunc/gmsh/_gmsh41.py
sgio/iofunc/nastran/_nastran.py
sgio/iofunc/swiftcomp/__init__.py
sgio/iofunc/swiftcomp/_global.py
sgio/iofunc/swiftcomp/_input.py
sgio/iofunc/swiftcomp/_mesh.py
sgio/iofunc/swiftcomp/_output.py
sgio/iofunc/swiftcomp/_swiftcomp.py
sgio/iofunc/vabs/__init__.py
sgio-0.2.15.dist-info/METADATA
sgio-0.2.15.dist-info/WHEEL
sgio-0.2.15.dist-info/entry_points.txt
sgio-0.2.15.dist-info/licenses/LICENSE
sgio-0.2.15.dist-info/RECORD
