Metadata-Version: 2.4
Name: sgio
Version: 0.2.15
Summary: I/O for VABS and SwiftComp
Project-URL: Homepage, https://github.com/wenbinyugroup/sgio
Project-URL: Documentation, https://wenbinyugroup.github.io/sgio/
Author-email: Su Tian <sutian@analyswift.com>
License-Expression: MIT
License-File: LICENSE
Classifier: Operating System :: OS Independent
Classifier: Programming Language :: Python :: 3
Requires-Python: >=3.9
Requires-Dist: build>=1.3.0
Requires-Dist: hatchling>=1.27.0
Requires-Dist: matplotlib
Requires-Dist: meshio
Requires-Dist: pydantic>=2.0
Requires-Dist: pyyaml
Requires-Dist: scipy
Requires-Dist: twine>=6.2.0
Provides-Extra: all
Requires-Dist: h5py; extra == 'all'
Requires-Dist: netcdf4; extra == 'all'
Requires-Dist: pytest; extra == 'all'
Provides-Extra: dev
Requires-Dist: pyinstaller; extra == 'dev'
Requires-Dist: pytest; extra == 'dev'
